{
  "depots": [
    { "id": "D1", "x": -77.2, "y": 38.9 },
    { "id": "D2", "x": -77.0, "y": 38.95 }
  ],
  "capacity": 60,
  "customers": [
    { "id": 1, "x": -77.18, "y": 38.92, "demand": 10, "earliest": 0, "latest": 240, "serviceTime": 5 },
    { "id": 2, "x": -77.25, "y": 38.91, "demand": 15, "earliest": 60, "latest": 360, "serviceTime": 5 },
    { "id": 3, "x": -77.05, "y": 38.97, "demand": 20, "earliest": 120, "latest": 420, "serviceTime": 10 },
    { "id": 4, "x": -77.00, "y": 38.90, "demand": 10, "earliest": 0, "latest": 600, "serviceTime": 5 },
    { "id": 5, "x": -77.12, "y": 38.88, "demand": 8,  "earliest": 30, "latest": 300, "serviceTime": 5 },
    { "id": 6, "x": -77.08, "y": 38.93, "demand": 12, "earliest": 200, "latest": 500, "serviceTime": 5 }
  ]
}


